db_lib/__init__.py
db_lib/crud.py
db_lib/database.py
db_lib/models.py
db_lib-0.2.0.dist-info/METADATA
db_lib-0.2.0.dist-info/WHEEL
db_lib-0.2.0.dist-info/top_level.txt
db_lib-0.2.0.dist-info/RECORD
