Metadata-Version: 2.1
Name: db-lib
Version: 0.2.0
Summary: Realtime project
Home-page: UNKNOWN
Author: Andrei Ponomarev
License: MIT
Platform: UNKNOWN
Requires-Dist: alembic (==1.7.4)
Requires-Dist: fastapi-sqlalchemy (==0.2.1)
Requires-Dist: psycopg2-binary (==2.9.1)
Requires-Dist: python-dotenv (==0.19.2)
